clase-4-4-23/e-01.vhdl
--sumador de 1 bit

library ieee;
use ieee.std_logic_1164.all;

entity p_fullAdder is
    port(
        DataIN :    in  STD_LOGIC_VECTOR(2 DOWNTO 0);
        D:          out STD_LOGIC_VECTOR(1 DOWNTO 0)
    );
    end p_fullAdder;


architecture behavioral of p_fullAdder is

begin

    
    process (DataIN) is
        begin
            case DataIN is 
                when "001" =>
                    D(0) <= '0' ;
                    D(1) <= '0' ;
                when "011" =>
                    D(0) <= '1' ;
                    D(1) <= '0' ;
                when "101" =>
                    D(0) <= '1' ;
                    D(1) <= '0' ;
                when "111" =>
                    D(0) <= '0' ;
                    D(1) <= '1' ;
                when "000" =>
                    D(0) <= '0' ;
                    D(1) <= '0' ;
                when "010" =>
                    D(0) <= '0' ;
                    D(1) <= '0' ;
                when "100" =>
                    D(0) <= '0' ;
                    D(1) <= '0' ;
                when "110" =>
                    D(0) <= '0' ;
                    D(1) <= '0' ;
                when others =>
                    D(0) <= 'X';
                    D(1) <= 'X';
            end case;
    end process; 

end behavioral;

clase-4-4-23/fa_tb.vhdl
library ieee;
use ieee.std_logic_1164.all;

entity fa_tb is
end fa_tb;

architecture behavior of fa_tb is
    component p_fullAdder is
        Port(
            DataIN     :  in STD_LOGIC_VECTOR(2 DOWNTO 0);
            D          : out STD_LOGIC_VECTOR(1 DOWNTO 0)                   
        );
    end component;

    signal A1     : std_ulogic;
    signal A2     : std_ulogic;
    signal A3     : std_ulogic;
    signal D1     : std_ulogic;
    signal D2     : std_ulogic;


begin
    uut: p_fullAdder port map(
        DataIN(0) => A1,
        DataIN(1) => A2,
        DataIN(2) => A3,
        D(0)      => D1,
        D(1)      => D2
    );

    process begin
        A1     <= 'X'; 
        A2     <= 'X';
        A3     <= 'X';
        wait for 1 ns;
        A1     <= '0'; 
        A2     <= '0';
        A3     <= '1';
        wait for 1 ns;
        A1     <= '0'; 
        A2     <= 'Z';
        A3     <= '1';
        wait for 1 ns;
        A1     <= '1'; 
        A2     <= '0';
        A3     <= '1';
        wait for 1 ns;
        A1     <= '1'; 
        A2     <= '1';
        A3     <= '1';
        wait for 1 ns;
        A1     <= '0'; 
        A2     <= '0';
        A3     <= '0';
        wait for 1 ns;
        A1     <= '0'; 
        A2     <= '1';
        A3     <= '0';
        wait for 1 ns;
        A1     <= '1'; 
        A2     <= '0';
        A3     <= '0';
        wait for 1 ns;
        A1     <= '1'; 
        A2     <= '1';
        A3     <= '0';
        wait for 1 ns;
        assert false report "Reached end of test";
        wait;
    end process;

end behavior;

clase-4-4-23/fa_tb.vcd
$date
  Tue Apr  4 18:01:24 2023
$end
$version
  GHDL v0
$end
$timescale
  1 fs
$end
$scope module standard $end
$upscope $end
$scope module std_logic_1164 $end
$upscope $end
$scope module fa_tb $end
$var reg 1 ! a1 $end
$var reg 1 " a2 $end
$var reg 1 # a3 $end
$var reg 1 $ d1 $end
$var reg 1 % d2 $end
$scope module uut $end
$var reg 3 & datain[2:0] $end
$var reg 2 ' d[1:0] $end
$upscope $end
$upscope $end
$enddefinitions $end
#0
X!
X"
X#
X$
X%
bXXX &
bXX '
#1000000
0!
0"
1#
0$
0%
b100 &
b00 '
#2000000
Z"
X$
X%
b1Z0 &
bXX '
#3000000
1!
0"
1$
0%
b101 &
b01 '
#4000000
1"
0$
1%
b111 &
b10 '
#5000000
0!
0"
0#
0%
b000 &
b00 '
#6000000
1"
b010 &
#7000000
1!
0"
b001 &
#8000000
1"
1$
b011 &
b01 '
