guia-entrenamiento/fullader-when/full-adder.vhdl
library ieee;
use ieee.std_logic_1164.all;

entity fa is
    port(
        A      : in     STD_LOGIC_VECTOR(1 DOWNTO 0);
        D      : out    STD_LOGIC_VECTOR(1 DOWNTO 0);
        ENABLE : in     STD_LOGIC       
    );
end fa;

architecture behavioral of fa is
begin
    D(0) <= A(0) AND A(1) when (ENABLE = '1') else '0' ;
    D(1) <= A(0) XOR A(1) when (ENABLE = '1') else '0' ; 
end behavioral;

guia-entrenamiento/ejercicio-01/e-01-1bit-adder-tb.vhdl
library ieee;
use ieee.std_logic_1164.all;

entity fa_tb is
end fa_tb;

architecture behavior of fa_tb is
    component fa is
        Port(
            A      :  in STD_LOGIC_VECTOR(1 DOWNTO 0);
            D      : out STD_LOGIC_VECTOR(1 DOWNTO 0); 
            ENABLE :  in STD_LOGIC                   
        );
    end component;

    signal A1     : std_ulogic;
    signal A2     : std_ulogic;
    signal D1     : std_ulogic;
    signal D2     : std_ulogic;
    signal ENABLE : std_ulogic;

begin
    uut: fa port map(
        A(0)    =>   A1,
        A(1)    =>   A2,
        D(0)    =>   D1,
        D(1)    =>   D2,
        ENABLE  => ENABLE
    );

    process begin
        A1     <= 'X'; 
        A2     <= 'X';
        ENABLE <= 'X';
        wait for 1 ns;
        A1     <= '0'; 
        A2     <= '0';
        ENABLE <= '1';
        wait for 1 ns;
        A1     <= '0'; 
        A2     <= '1';
        ENABLE <= '1';
        wait for 1 ns;
        A1     <= '1'; 
        A2     <= '0';
        ENABLE <= '1';
        wait for 1 ns;
        A1     <= '1'; 
        A2     <= '1';
        ENABLE <= '1';
        wait for 1 ns;
        A1     <= '0'; 
        A2     <= '0';
        ENABLE <= '0';
        wait for 1 ns;
        A1     <= '0'; 
        A2     <= '1';
        ENABLE <= '0';
        wait for 1 ns;
        A1     <= '1'; 
        A2     <= '0';
        ENABLE <= '0';
        wait for 1 ns;
        A1     <= '1'; 
        A2     <= '1';
        ENABLE <= '0';
        wait for 1 ns;
        assert false report "Reached end of test";
        wait;
    end process;

end behavior;

guia-entrenamiento/fullader-when/fa_tb.vcd
$date
  Sat Mar 25 19:01:41 2023
$end
$version
  GHDL v0
$end
$timescale
  1 fs
$end
$scope module standard $end
$upscope $end
$scope module std_logic_1164 $end
$upscope $end
$scope module fa_tb $end
$var reg 1 ! a1 $end
$var reg 1 " a2 $end
$var reg 1 # d1 $end
$var reg 1 $ d2 $end
$var reg 1 % enable $end
$scope module uut $end
$var reg 2 & a[1:0] $end
$var reg 2 ' d[1:0] $end
$var reg 1 ( enable $end
$upscope $end
$upscope $end
$enddefinitions $end
#0
X!
X"
0#
0$
X%
bXX &
b00 '
X(
#1000000
0!
0"
1%
b00 &
1(
#2000000
1"
1$
b10 &
b10 '
#3000000
1!
0"
b01 &
#4000000
1"
1#
0$
b11 &
b01 '
#5000000
0!
0"
0#
0%
b00 &
b00 '
0(
#6000000
1"
b10 &
#7000000
1!
0"
b01 &
#8000000
1"
b11 &
